Tabla_03_POS/Tabla03_POS.v
module Tabla03_POS();

  reg A, B, C, D;
  wire S1, S2, S3, S4, S5, S6, S7, S8, S9, S10, S11, S12, S13, out;

  not N1(S1, A);
  not N2(S2, B);
  not N3(S3, C);
  not N4(S4, D);
  or N5(S5, A, S2, C, D);
  or N6(S6, A, S2, C, S4);
  or N7(S7, A, S2, S3, D);
  or N8(S8, A, S2, S3, S4);
  or N9(S9, S1, B, C, S4);
  or N10(S10, S1, B, S3, S4);
  or N11(S11, S1, S2, C, D);
  or N12(S12, S1, S2, C, S4);
  or N13(S13, S1, S2, S3, S4);
  and N14(out, S5, S6, S7, S8, S9, S10, S11, S12, S13);

  initial begin
    $display("A B C D | Y");
    $monitor("%b %b %b %b | %b", A, B, C, D, out);
    A=0; B=0; C=0; D=0;
    #1 D=1;
    #1 C=1; D=0;
    #1 D=1;
    #1 B=1; C=0; D=0;
    #1 D=1;
    #1 C=1; D=0;
    #1 D=1;
    #1 A=1; B=0; C=0; D=0;
    #1 D=1;
    #1 C=1; D=0;
    #1 D=1;
    #1 B=1; C=0; D=0;
    #1 D=1;
    #1 C=1; D=0;
    #1 D=1;
    #1 $finish;
  end

/*
  initial   //Esta parte esta comentada debido a que despues de ejecutarlo una ves deja de mostrar la tabla de verdad
    begin   //Si desea ver la gráfica por Gtkwave quite los "/*" al inicio y al final
      $dumpfile("Tabla03_POS_tb.vcd");
      $dumpvars(0, Tabla03_POS);
    end
*/

endmodule

Tabla_03_POS/Tabla03_POS_tb.vcd
$date
	Thu Jul 30 16:07:10 2020
$end
$version
	Icarus Verilog
$end
$timescale
	1ps
$end
$scope module Tabla03_POS $end
$var wire 1 ! S1 $end
$var wire 1 " S10 $end
$var wire 1 # S11 $end
$var wire 1 $ S12 $end
$var wire 1 % S13 $end
$var wire 1 & S2 $end
$var wire 1 ' S3 $end
$var wire 1 ( S4 $end
$var wire 1 ) S5 $end
$var wire 1 * S6 $end
$var wire 1 + S7 $end
$var wire 1 , S8 $end
$var wire 1 - S9 $end
$var wire 1 . out $end
$var reg 1 / A $end
$var reg 1 0 B $end
$var reg 1 1 C $end
$var reg 1 2 D $end
$upscope $end
$enddefinitions $end
#0
$dumpvars
02
01
00
0/
1.
1-
1,
1+
1*
1)
1(
1'
1&
1%
1$
1#
1"
1!
$end
#1
0(
12
#2
1(
0'
02
11
#3
0(
12
#4
0.
1(
1*
0)
1'
0&
02
01
10
#5
0*
1)
0(
12
#6
0+
1(
1*
0'
02
11
#7
0,
1+
0(
12
#8
1.
1(
1'
1"
1-
1&
1,
0!
02
01
00
1/
#9
0.
0-
0(
12
#10
1.
1(
1-
0'
02
11
#11
0.
0"
0(
12
#12
1(
1$
0#
1'
1"
0&
02
01
10
#13
0$
1#
0(
12
#14
1.
1(
1$
0'
02
11
#15
0.
0%
0(
12
